geojson_rewind/__init__.py
geojson_rewind/rewind.py
geojson_rewind-1.2.0.dist-info/METADATA
geojson_rewind-1.2.0.dist-info/WHEEL
geojson_rewind-1.2.0.dist-info/entry_points.txt
geojson_rewind-1.2.0.dist-info/licenses/LICENSE
geojson_rewind-1.2.0.dist-info/RECORD
