Metadata-Version: 2.4
Name: geojson-rewind
Version: 1.2.0
Summary: A Python library for enforcing polygon ring winding order in GeoJSON
License-Expression: MIT
License-File: LICENSE
Author: chris48s
Requires-Python: >=3.10
Classifier: Programming Language :: Python :: 3
Classifier: Programming Language :: Python :: 3.10
Classifier: Programming Language :: Python :: 3.11
Classifier: Programming Language :: Python :: 3.12
Classifier: Programming Language :: Python :: 3.13
Classifier: Programming Language :: Python :: 3.14
Project-URL: Home, https://github.com/chris48s/geojson-rewind
Project-URL: Source, https://github.com/chris48s/geojson-rewind
